esi_core/gmprocess/__init__.py
esi_core/gmprocess/metrics/__init__.py
esi_core/gmprocess/metrics/cfuncs.c
esi_core/gmprocess/metrics/cfuncs.h
esi_core/gmprocess/metrics/oscillators.c
esi_core/gmprocess/metrics/oscillators.cpython-310-x86_64-linux-gnu.so
esi_core/gmprocess/metrics/oscillators.pyx
esi_core/gmprocess/waveform_processing/__init__.py
esi_core/gmprocess/waveform_processing/auto_fchp.c
esi_core/gmprocess/waveform_processing/auto_fchp.cpython-310-x86_64-linux-gnu.so
esi_core/gmprocess/waveform_processing/auto_fchp.pyx
esi_core/gmprocess/waveform_processing/smoothing/__init__.py
esi_core/gmprocess/waveform_processing/smoothing/konno_ohmachi.c
esi_core/gmprocess/waveform_processing/smoothing/konno_ohmachi.cpython-310-x86_64-linux-gnu.so
esi_core/gmprocess/waveform_processing/smoothing/konno_ohmachi.pyx
esi_core/gmprocess/waveform_processing/smoothing/smoothing.c
esi_core/gmprocess/waveform_processing/smoothing/smoothing.h
esi_core/shakemap/__init__.py
esi_core/shakemap/contour.c
esi_core/shakemap/contour.h
esi_core/shakemap/covariance_matrix.c
esi_core/shakemap/covariance_matrix.cpython-310-x86_64-linux-gnu.so
esi_core/shakemap/covariance_matrix.pyx
esi_core/shakemap/geodetic_distances.c
esi_core/shakemap/geodetic_distances.cpython-310-x86_64-linux-gnu.so
esi_core/shakemap/geodetic_distances.pyx
esi_core/shakemap/pcontour.c
esi_core/shakemap/pcontour.cpython-310-x86_64-linux-gnu.so
esi_core/shakemap/pcontour.pyx
esi_core-1.2.3.dist-info/METADATA
esi_core-1.2.3.dist-info/WHEEL
esi_core-1.2.3.dist-info/top_level.txt
esi_core-1.2.3.dist-info/RECORD
esi_core-1.2.3.dist-info/licenses/LICENSE.md
