Metadata-Version: 2.4
Name: esi-core
Version: 1.2.3
Summary: Repository for compiled code used by ESI projects.
Author-email: Eric Thompson <emthompsone@usgs.gov>, Bruce Worden <cbworden@contractor.usgs.gov>, Gabe Ferragut <gferragut@usgs.gov>
License: License
Requires-Python: <3.13,>=3.9
License-File: LICENSE.md
Requires-Dist: numpy>=1.26
Requires-Dist: obspy>=1.3.1
Requires-Dist: six>=1.16
Provides-Extra: dev
Requires-Dist: build>=0.7.0; extra == "dev"
Requires-Dist: black>=21; extra == "dev"
Requires-Dist: flake8>=3.9; extra == "dev"
Requires-Dist: ipython>=7.26; extra == "dev"
Provides-Extra: test
Requires-Dist: pytest>=6.2; extra == "test"
Requires-Dist: pytest-cov>=2.12; extra == "test"
Requires-Dist: pytest-console-scripts>=1.2; extra == "test"
Requires-Dist: vcrpy>=4.1; extra == "test"
Provides-Extra: build
Requires-Dist: build; extra == "build"
Requires-Dist: twine; extra == "build"
Requires-Dist: check-wheel-contents; extra == "build"
Dynamic: license-file
